MANIFEST.in
setup.py
parent_swap/__init__.py
parent_swap/swap.py
parent_swap.egg-info/PKG-INFO
parent_swap.egg-info/SOURCES.txt
parent_swap.egg-info/dependency_links.txt
parent_swap.egg-info/pbr.json
parent_swap.egg-info/requires.txt
parent_swap.egg-info/top_level.txt
parent_swap/tests/__init__.py
parent_swap/tests/runtests.py
parent_swap/tests/test_swap.py
parent_swap/tests/utils.py
parent_swap/tests/parent_app/__init__.py
parent_swap/tests/parent_app/models.py
parent_swap/tests/parent_app/serializers.py
parent_swap/tests/parent_app/views.py
parent_swap/tests/simple_app/__init__.py
parent_swap/tests/simple_app/models.py
parent_swap/tests/simple_app/serializers.py
parent_swap/tests/simple_app/views.py