Metadata-Version: 1.0
Name: parent-swap
Version: 0.0.3
Summary: Replace abstract parent classes of django objects
Home-page: UNKNOWN
Author: Cameron Lowe
Author-email: clowe@theonion.com
License: MIT
Platform: UNKNOWN
